terrier/__init__.py
terrier/apps.py
terrier/data/repbase-to-repeatmasker.toml
terrier/data/repbase.tree.txt
terrier/defaults.py
terrier/evaluate.py
terrier/repeatmasker.py
terrier/terrier.bib
bio_terrier-0.3.4.dist-info/LICENSE
bio_terrier-0.3.4.dist-info/METADATA
bio_terrier-0.3.4.dist-info/WHEEL
bio_terrier-0.3.4.dist-info/entry_points.txt
bio_terrier-0.3.4.dist-info/RECORD
