Metadata-Version: 2.3
Name: bio-terrier
Version: 0.3.4
Summary: Transposable Element Repeat Result classifIER
License: Apache-2.0
Keywords: torchapp,pytorch,deep learning,command-line interface
Author: Robert Turnbull
Author-email: robert.turnbull@unimelb.edu.au
Requires-Python: >=3.10,<3.13
Classifier: Intended Audience :: Science/Research
Classifier: License :: OSI Approved :: Apache Software License
Classifier: Programming Language :: Python :: 3
Classifier: Programming Language :: Python :: 3.10
Classifier: Programming Language :: Python :: 3.11
Classifier: Programming Language :: Python :: 3.12
Classifier: Topic :: Scientific/Engineering :: Artificial Intelligence
Classifier: Topic :: Software Development :: Libraries :: Python Modules
Requires-Dist: bio-corgi (>=0.5.1)
Requires-Dist: h5py (>=3.8.0)
Requires-Dist: numpy (<2.0.0)
Requires-Dist: pandas (<=2.2.0)
Requires-Dist: pyfastx (>=1.1.0)
Requires-Dist: toml (>=0.10.2)
Project-URL: Documentation, https://rbturnbull.github.io/terrier
Project-URL: Homepage, https://github.com/rbturnbull/terrier/
Project-URL: Repository, https://github.com/rbturnbull/terrier/
